hyper_connections/__init__.py
hyper_connections/hyper_connections.py
hyper_connections/hyper_connections_channel_first.py
hyper_connections/hyper_connections_with_multi_branch_inputs.py
hyper_connections/hyper_connections_with_multi_input_streams.py
hyper_connections/mHCv2.py
hyper_connections/manifold_constrained_hyper_connections.py
hyper_connections/residuals.py
hyper_connections/triton_sinkhorn.py
hyper_connections/vit.py
hyper_connections-0.4.7.dist-info/METADATA
hyper_connections-0.4.7.dist-info/WHEEL
hyper_connections-0.4.7.dist-info/licenses/LICENSE
hyper_connections-0.4.7.dist-info/RECORD
