Metadata-Version: 2.4
Name: hyper-connections
Version: 0.4.7
Summary: Hyper-Connections
Project-URL: Homepage, https://pypi.org/project/hyper-connections/
Project-URL: Repository, https://github.com/lucidrains/hyper-connections
Author-email: Phil Wang <lucidrains@gmail.com>
License: MIT License
License-File: LICENSE
Keywords: artificial intelligence,deep learning,residual
Classifier: Development Status :: 4 - Beta
Classifier: Intended Audience :: Developers
Classifier: License :: OSI Approved :: MIT License
Classifier: Programming Language :: Python :: 3.9
Classifier: Topic :: Scientific/Engineering :: Artificial Intelligence
Requires-Python: >=3.9
Requires-Dist: einops>=0.8.1
Requires-Dist: torch>=2.5
Provides-Extra: examples
